Metadata-Version: 2.1
Name: organization-map
Version: 1.0.5
Summary: Creates an organization map image
Home-page: https://github.com/snuids/organization_map
Author: snuids
Author-email: snuids@mannekentech.com
License: UNKNOWN
Download-URL: https://github.com/snuids/organization_map/archive/1.0.5.tar.gz
Keywords: Python,image,hierarchical,tree,diagram
Platform: UNKNOWN
